HuffmanCoder/HuffmanCoder.py
HuffmanCoder/TreeNode.py
HuffmanCoder/__init__.py
HuffmanCoder-0.0.32.dist-info/METADATA
HuffmanCoder-0.0.32.dist-info/WHEEL
HuffmanCoder-0.0.32.dist-info/top_level.txt
HuffmanCoder-0.0.32.dist-info/RECORD
