Metadata-Version: 2.1
Name: HuffmanCoder
Version: 0.0.32
Summary: simple Huffman encoder
Home-page: https://github.com/ShikharSahu/HuffmanCoder
Author: Shikhar Sahu
Author-email: <shikharsahu76@gmail.com>
License: UNKNOWN
Keywords: python,huffman,encoding,decoding,data,compression
Platform: UNKNOWN
Classifier: Development Status :: 3 - Alpha
Classifier: Intended Audience :: Developers
Classifier: Programming Language :: Python :: 3
Classifier: Operating System :: Unix
Classifier: Operating System :: MacOS :: MacOS X
Classifier: Operating System :: Microsoft :: Windows
